pywchat/__init__.py
pywchat/chatapi.py
pywchat/send.py
pywchat/workhandler.py
pywchat-1.5.0.dist-info/LICENSE
pywchat-1.5.0.dist-info/METADATA
pywchat-1.5.0.dist-info/WHEEL
pywchat-1.5.0.dist-info/top_level.txt
pywchat-1.5.0.dist-info/RECORD
