Metadata-Version: 2.1
Name: pywchat
Version: 1.5.0
Summary: Custom WeChat push information database
Home-page: https://github.com/HangJau/pywchat
Author: Hangjau
Author-email: hangjau818@gmail.com
Platform: any
Classifier: Programming Language :: Python :: 3
Classifier: License :: OSI Approved :: GNU General Public License (GPL)
Classifier: Operating System :: OS Independent
License-File: LICENSE
Requires-Dist: requests >=2.22.0
